diffidm/__init__.py
diffidm/layer.py
diffidm-0.0.3.dist-info/LICENSE
diffidm-0.0.3.dist-info/METADATA
diffidm-0.0.3.dist-info/WHEEL
diffidm-0.0.3.dist-info/top_level.txt
diffidm-0.0.3.dist-info/RECORD
