Metadata-Version: 2.2
Name: diffidm
Version: 0.0.3
Summary: Parallelized differentiable IDM computation layer for traffic simulation
Author-email: Sanghyun Son <shh1295@umd.edu>, Laura Zheng <lyzheng@umd.edu>
License: MIT License
Project-URL: Homepage, https://github.com/SonSang/diffidm
Keywords: traffic,parallelized,differentiable,trajectory,optimization
Classifier: Development Status :: 3 - Alpha
Classifier: Programming Language :: Python :: 3
Classifier: License :: OSI Approved :: MIT License
Classifier: Operating System :: OS Independent
Requires-Python: >=3.7
License-File: LICENSE
Requires-Dist: torch
Requires-Dist: numpy
